jmunja/__init__.py
jmunja/example.py
jmunja/smssend.py
jmunja-0.0.4.dist-info/METADATA
jmunja-0.0.4.dist-info/WHEEL
jmunja-0.0.4.dist-info/top_level.txt
jmunja-0.0.4.dist-info/RECORD
