Metadata-Version: 2.1
Name: jmunja
Version: 0.0.4
Summary: Jmunja message send package
Home-page: https://github.com/nicecoding1/jmunja
Author: Jaesang Jo
Author-email: oralol@naver.com
License: UNKNOWN
Platform: UNKNOWN
Classifier: Programming Language :: Python :: 3
Classifier: License :: OSI Approved :: MIT License
Classifier: Operating System :: OS Independent
Requires-Python: >=3.6
